{
  "ret": true,
  "data": [
    {
      "id": 1,
      "imgUrl": "http://www.res.ren3.pandadastudio.com/upload/default/20200728/17b2ec0074a163a768871ed789878898.jpg",
      "title": "河豚团本最高成绩————197",
      "describe": ""
    },
    {
      "id": 2,
      "imgUrl": "http://www.res.ren3.pandadastudio.com/upload/default/20200728/ef34730d60d3f3a3051cc479b3fa784c.jpg",
      "title": "S9赛季卡牌详解",
      "describe": ""
    },
    {
      "id": 3,
      "imgUrl": "http://www.res.ren3.pandadastudio.com/upload/default/20200728/c43ef3ebbb5ed5873daadf4cd859cd92.jpg",
      "title": "猫老师小课堂——武器养成优先级",
      "describe": ""
    },
    {
      "id": 4,
      "imgUrl": "http://www.res.ren3.pandadastudio.com/upload/default/20200728/5bc238b3d18ca8c7fd0afcc56910451b.jpg",
      "title": "S9赛季——颗粒无收卡牌详解",
      "describe": ""
    }
  ]
}
